cython_extensions/ability_mapping.pxd
cython_extensions/combat_utils.pyx
cython_extensions/map_analysis.pyi
cython_extensions/units_utils.pyx
cython_extensions/placement_solver.pyx
cython_extensions/bootstrap.pyx
cython_extensions/numpy_helper.pyi
cython_extensions/general_utils.pyx
cython_extensions/turn_rate.pyx
cython_extensions/dijkstra.pyi
cython_extensions/__init__.py
cython_extensions/geometry.pyi
cython_extensions/combat_utils.pyi
cython_extensions/map_analysis.pyx
cython_extensions/bootstrap.cpython-312-darwin.so
cython_extensions/units_utils.pyi
cython_extensions/placement_solver.pyi
cython_extensions/ability_order_tracker.pyx
cython_extensions/general_utils.pyi
cython_extensions/numpy_helper.pyx
cython_extensions/dijkstra.pyx
cython_extensions/ability_mapping.pyx
cython_extensions/unit_data.pyx
cython_extensions/geometry.pyx
cython_extensions/type_checking/config.py
cython_extensions/type_checking/validators.py
cython_extensions/type_checking/__init__.py
cython_extensions/type_checking/wrappers.py
cython_extensions_sc2-0.13.1.dist-info/RECORD
cython_extensions_sc2-0.13.1.dist-info/LICENSE
cython_extensions_sc2-0.13.1.dist-info/WHEEL
cython_extensions_sc2-0.13.1.dist-info/METADATA
