Metadata-Version: 2.1
Name: cython-extensions-sc2
Version: 0.13.1
Summary: 
License: GPL-3.0
Author: Tom Kerr
Author-email: tomkerrdev@gmail.com
Requires-Python: >=3.11,<3.14
Classifier: License :: OSI Approved :: GNU General Public License v3 (GPLv3)
Classifier: Programming Language :: Python :: 3
Classifier: Programming Language :: Python :: 3.11
Classifier: Programming Language :: Python :: 3.12
Classifier: Programming Language :: Python :: 3.13
Requires-Dist: burnysc2 (>=7.0.0)
Requires-Dist: jupyterlab (>=4.4.6,<5.0.0)
